{
  "routes": [
    {
      "method": "GET",
      "path": "/funds",
      "handler": "funds.find",
      "config": {
        "policies": []
      }
    },
    {
      "method": "GET",
      "path": "/funds/count",
      "handler": "funds.count",
      "config": {
        "policies": []
      }
    },
    {
      "method": "GET",
      "path": "/funds/:id",
      "handler": "funds.findOne",
      "config": {
        "policies": []
      }
    },
    {
      "method": "POST",
      "path": "/funds",
      "handler": "funds.create",
      "config": {
        "policies": []
      }
    },
    {
      "method": "PUT",
      "path": "/funds/:id",
      "handler": "funds.update",
      "config": {
        "policies": []
      }
    },
    {
      "method": "DELETE",
      "path": "/funds/:id",
      "handler": "funds.delete",
      "config": {
        "policies": []
      }
    }
  ]
}
